fileware/__init__.py
fileware/cert.py
fileware/models.py
fileware/ngrok.py
fileware/requirements.txt
fileware/responder.py
fileware/server.py
fileware/settings.py
fileware/helpers/volume.py
fileware/html/auth_server.html
fileware/html/no_auth.html
fileware/html/session.html
fileware-1.3.dist-info/LICENSE
fileware-1.3.dist-info/METADATA
fileware-1.3.dist-info/WHEEL
fileware-1.3.dist-info/top_level.txt
fileware-1.3.dist-info/RECORD
