Metadata-Version: 2.1
Name: fileware
Version: 1.3
Summary: Python module to, serve files in physical memory to localhost and tunnel to a public endpoint
Author-email: Vignesh Rao <svignesh1793@gmail.com>
License: MIT License
Project-URL: Homepage, https://github.com/thevickypedia/fileware
Project-URL: Docs, https://thevickypedia.github.io/fileware
Project-URL: Source, https://github.com/thevickypedia/fileware
Project-URL: Bug Tracker, https://github.com/thevickypedia/fileware/issues
Project-URL: Release Notes, https://github.com/thevickypedia/fileware/blob/main/release_notes.rst
Keywords: personal-cloud,file-server,ssl
Classifier: Development Status :: 5 - Production/Stable
Classifier: Intended Audience :: Information Technology
Classifier: Operating System :: OS Independent
Classifier: License :: OSI Approved :: MIT License
Classifier: Programming Language :: Python :: 3.8
Classifier: Programming Language :: Python :: 3.9
Classifier: Programming Language :: Python :: 3.10
Classifier: Programming Language :: Python :: 3.11
Classifier: Topic :: Internet :: WWW/HTTP :: HTTP Servers
Requires-Python: >=3.8
License-File: LICENSE
Requires-Dist: gmail-connector >=0.6.0
Requires-Dist: pyngrok >=5.2.1
Requires-Dist: pyOpenSSL >=22.0.0
Requires-Dist: python-dotenv >=0.19.2
Requires-Dist: PyYAML >=6.0
Requires-Dist: requests >=2.27.1
Provides-Extra: dev
Requires-Dist: sphinx ==5.1.1 ; extra == 'dev'
Requires-Dist: pre-commit ; extra == 'dev'
Requires-Dist: recommonmark ; extra == 'dev'
Requires-Dist: pytest ; extra == 'dev'
